{
  "_comment": "Essential Theme Configuration - Light and Dark themes with orange accents",
  "Dark": {
    "name": "Dark",
    "colors": {
      "background": "#2b2b2b",
      "surface": "#353535",
      "primary": "#42a5f5",
      "secondary": "#9e9e9e",
      "accent": "#ff7043",
      
      "text_primary": "#c5c5c5",
      "text_secondary": "#b0b0b0",
      "text_disabled": "#707070",
      "text_inverse": "#2b2b2b",
      
      "button_normal": "#404040",
      "button_hover": "#4a4a4a",
      "button_pressed": "#555555",
      
      "selection_background": "#42a5f5",
      "selection_text": "#ffffff",
      "selection_inactive": "#64b5f6",
      "hover_background": "#3a3a3a",
      
      "editor_background": "#2e2e2e",
      "editor_text": "#e0e0e0",
      "editor_line_number_bg": "#353535",
      "editor_line_number_text": "#9e9e9e",
      "editor_current_line": "#383838",
      "editor_selection": "#1976d2",
      
      "table_background": "#2b2b2b",
      "table_alternate": "#353535",
      "table_header_bg": "#404040",
      "table_header_text": "#e0e0e0",
      "table_border": "#555555",
      
      "success": "#66bb6a",
      "warning": "#ffb74d",
      "error": "#ef5350",
      "info": "#42a5f5",
      
      "splitter_handle": "#555555",
      "splitter_pressed": "#606060",
      
      "tab_active_bg": "#2e2e2e",
      "tab_active_text": "#e0e0e0",
      "tab_inactive_bg": "#404040",
      "tab_inactive_text": "#b0b0b0",
      
      "scrollbar_background": "#3a3a3a",
      "scrollbar_handle": "#555555",
      "scrollbar_handle_hover": "#666666",
      
      "checkbox_background": "#2e2e2e",
      "checkbox_border": "#555555",
      "checkbox_checked_border": "#42a5f5",
      "checkbox_checked_mark": "#42a5f5",
      "checkbox_hover_border": "#64b5f6",
      "checkbox_indeterminate": "#ffb74d",
      
      "syntax_keyword": "#64b5f6",
      "syntax_logic": "#ba68c8",
      "syntax_builtin": "#4dd0e1",
      "syntax_modifier": "#ffcc02",
      "syntax_module": "#81c784",
      "syntax_symbol": "#90caf9",
      "syntax_number": "#a5d6a7",
      "syntax_string": "#ffcc80",
      "syntax_regex": "#f48fb1",
      "syntax_hex": "#ffe082",
      "syntax_comment": "#81c784",
      "syntax_identifier": "#90caf9",
      "syntax_meta_key": "#4dd0e1",
      "syntax_tag": "#ffcc02",
      "syntax_condition": "#ba68c8",
      "syntax_operator": "#e0e0e0",
      "syntax_literal": "#ffcc80",
      "syntax_function": "#81c784",
      "syntax_section": "#64b5f6",
      
      "column_file": "#323536",
      "column_rule": "#2f3234",
      "column_pattern": "#363234",
      "column_offset": "#343032",
      "column_data": "#303634",
      "column_hex": "#2e3436"
    },
    "font_family": "Segoe UI",
    "font_size": 9,
    "editor_font_family": "Consolas",
    "editor_font_size": 11,
    "border_radius": 4,
    "border_width": 1,
    "padding_small": 4,
    "padding_medium": 8,
    "padding_large": 12,
    "animation_duration": 150
  },

  "Light": {
    "name": "Light",
    "colors": {
      "background": "#ffffff",
      "surface": "#f8f9fa",
      "primary": "#0066cc",
      "secondary": "#6c757d",
      "accent": "#ff6600",
      
      "text_primary": "#4a4a4a",
      "text_secondary": "#6c757d",
      "text_disabled": "#adb5bd",
      "text_inverse": "#ffffff",
      
      "button_normal": "#e9ecef",
      "button_hover": "#dee2e6",
      "button_pressed": "#ced4da",
      
      "selection_background": "#cce7ff",
      "selection_text": "#212529",
      "selection_inactive": "#e6f3ff",
      "hover_background": "#f1f3f4",
      
      "editor_background": "#ffffff",
      "editor_text": "#212529",
      "editor_line_number_bg": "#f8f9fa",
      "editor_line_number_text": "#6c757d",
      "editor_current_line": "#c4d9ff",
      "editor_selection": "#cce7ff",
      
      "table_background": "#ffffff",
      "table_alternate": "#f8f9fa",
      "table_header_bg": "#e9ecef",
      "table_header_text": "#495057",
      "table_border": "#dee2e6",
      
      "success": "#198754",
      "warning": "#fd7e14",
      "error": "#dc3545",
      "info": "#0d6efd",
      
      "splitter_handle": "#dee2e6",
      "splitter_pressed": "#ced4da",
      
      "tab_active_bg": "#ffffff",
      "tab_active_text": "#212529",
      "tab_inactive_bg": "#f8f9fa",
      "tab_inactive_text": "#6c757d",
      
      "scrollbar_background": "#f8f9fa",
      "scrollbar_handle": "#ced4da",
      "scrollbar_handle_hover": "#adb5bd",
      
      "checkbox_background": "#ffffff",
      "checkbox_border": "#ced4da",
      "checkbox_checked_border": "#ff6600",
      "checkbox_checked_mark": "#ff6600",
      "checkbox_hover_border": "#ff6600",
      "checkbox_indeterminate": "#fd7e14",
      
      "syntax_keyword": "#0033cc",
      "syntax_logic": "#6600cc",
      "syntax_builtin": "#cc4400",
      "syntax_modifier": "#663300",
      "syntax_module": "#006633",
      "syntax_symbol": "#000099",
      "syntax_number": "#006600",
      "syntax_string": "#990000",
      "syntax_regex": "#990033",
      "syntax_hex": "#cc6600",
      "syntax_comment": "#006600",
      "syntax_identifier": "#ff6600",
      "syntax_meta_key": "#cc4400",
      "syntax_tag": "#663300",
      "syntax_condition": "#6600cc",
      "syntax_operator": "#333333",
      "syntax_literal": "#990000",
      "syntax_function": "#006633",
      "syntax_section": "#0033cc",
      
      "column_file": "#fefdfb",
      "column_rule": "#fbfef9",
      "column_pattern": "#fefcf9",
      "column_offset": "#fef9fc",
      "column_data": "#f9fefb",
      "column_hex": "#f9fcfe"
    },
    "font_family": "Segoe UI",
    "font_size": 9,
    "editor_font_family": "Consolas",
    "editor_font_size": 11,
    "border_radius": 4,
    "border_width": 1,
    "padding_small": 4,
    "padding_medium": 8,
    "padding_large": 12,
    "animation_duration": 200
  },

  "Custom Dark Blue": {
    "name": "Custom Dark Blue",
    "colors": {
      "background": "#1a1a2e",
      "surface": "#16213e",
      "primary": "#0f3460",
      "secondary": "#533483",
      "accent": "#e94560",
      
      "text_primary": "#b8b5b5",
      "text_secondary": "#a0a0a0",
      "text_disabled": "#606060",
      "text_inverse": "#1a1a2e",
      
      "button_normal": "#16213e",
      "button_hover": "#0f3460",
      "button_pressed": "#533483",
      
      "selection_background": "#e94560",
      "selection_text": "#ffffff",
      "selection_inactive": "#e94560",
      "hover_background": "#0f3460",
      
      "editor_background": "#0e1629",
      "editor_text": "#eee6e6",
      "editor_line_number_bg": "#16213e",
      "editor_line_number_text": "#a0a0a0",
      "editor_current_line": "#16213e",
      "editor_selection": "#0f3460",
      
      "table_background": "#1a1a2e",
      "table_alternate": "#16213e",
      "table_header_bg": "#0f3460",
      "table_header_text": "#eee6e6",
      "table_border": "#533483",
      
      "success": "#27ae60",
      "warning": "#f39c12",
      "error": "#e94560",
      "info": "#3498db",
      
      "splitter_handle": "#533483",
      "splitter_pressed": "#e94560",
      
      "tab_active_bg": "#1a1a2e",
      "tab_active_text": "#eee6e6",
      "tab_inactive_bg": "#16213e",
      "tab_inactive_text": "#a0a0a0",
      
      "scrollbar_background": "#0e1629",
      "scrollbar_handle": "#533483",
      "scrollbar_handle_hover": "#e94560",
      "checkbox_background": "#1a1a2e",
      "checkbox_border": "#533483",
      "checkbox_checked_border": "#e94560",
      "checkbox_checked_mark": "#e94560",
      "checkbox_hover_border": "#0f3460",
      "checkbox_indeterminate": "#f39c12",
      "syntax_keyword": "#7cb7f7",
      "syntax_logic": "#e291d9",
      "syntax_builtin": "#4fd1e7",
      "syntax_modifier": "#fff176",
      "syntax_module": "#81c784",
      "syntax_symbol": "#90caf9",
      "syntax_number": "#a5d6a7",
      "syntax_string": "#ffcc80",
      "syntax_regex": "#f8bbd9",
      "syntax_hex": "#ffe082",
      "syntax_comment": "#81c784",
      "syntax_identifier": "#ffa366",
      "syntax_meta_key": "#4fd1e7",
      "syntax_tag": "#fff176",
      "syntax_condition": "#e291d9",
      "syntax_operator": "#b0bec5",
      "syntax_literal": "#ffcc80",
      "syntax_function": "#81c784",
      "syntax_section": "#7cb7f7",
      "column_file": "#1e2025",
      "column_rule": "#1f2127",
      "column_pattern": "#252024",
      "column_offset": "#241f22",
      "column_data": "#202523",
      "column_hex": "#222420"
    },
    "font_family": "Segoe UI",
    "font_size": 9,
    "editor_font_family": "Consolas",
    "editor_font_size": 10,
    "border_radius": 6,
    "border_width": 1,
    "padding_small": 4,
    "padding_medium": 8,
    "padding_large": 12,
    "animation_duration": 200
  },
  
  "High Contrast": {
    "name": "High Contrast",
    "colors": {
      "background": "#000000",
      "surface": "#1a1a1a",
      "primary": "#ffffff",
      "secondary": "#808080",
      "accent": "#ffff00",
      
      "text_primary": "#d0d0d0",
      "text_secondary": "#c0c0c0",
      "text_disabled": "#808080",
      "text_inverse": "#000000",
      
      "button_normal": "#1a1a1a",
      "button_hover": "#333333",
      "button_pressed": "#4d4d4d",
      
      "selection_background": "#ffff00",
      "selection_text": "#000000",
      "selection_inactive": "#ffff00",
      "hover_background": "#333333",
      
      "editor_background": "#000000",
      "editor_text": "#ffffff",
      "editor_line_number_bg": "#1a1a1a",
      "editor_line_number_text": "#c0c0c0",
      "editor_current_line": "#1a1a1a",
      "editor_selection": "#0080ff",
      
      "table_background": "#000000",
      "table_alternate": "#1a1a1a",
      "table_header_bg": "#333333",
      "table_header_text": "#ffffff",
      "table_border": "#808080",
      
      "success": "#00ff00",
      "warning": "#ffff00",
      "error": "#ff0000",
      "info": "#00ffff",
      
      "splitter_handle": "#808080",
      "splitter_pressed": "#ffffff",
      
      "tab_active_bg": "#000000",
      "tab_active_text": "#ffffff",
      "tab_inactive_bg": "#1a1a1a",
      "tab_inactive_text": "#c0c0c0",
      
      "scrollbar_background": "#1a1a1a",
      "scrollbar_handle": "#808080",
      "scrollbar_handle_hover": "#ffffff",
      "checkbox_background": "#ffffff",
      "checkbox_border": "#808080",
      "checkbox_checked_border": "#ffff00",
      "checkbox_checked_mark": "#ffff00",
      "checkbox_hover_border": "#ffffff",
      "checkbox_indeterminate": "#808080",
      "syntax_keyword": "#00ffff",
      "syntax_logic": "#ff00ff",
      "syntax_builtin": "#00ff00",
      "syntax_modifier": "#ffff00",
      "syntax_module": "#ffffff",
      "syntax_symbol": "#87ceeb",
      "syntax_number": "#90ee90",
      "syntax_string": "#ffa500",
      "syntax_regex": "#ff69b4",
      "syntax_hex": "#ffd700",
      "syntax_comment": "#32cd32",
      "syntax_identifier": "#ffaa00",
      "syntax_meta_key": "#00ff00",
      "syntax_tag": "#ffff00",
      "syntax_condition": "#ff00ff",
      "syntax_operator": "#c0c0c0",
      "syntax_literal": "#ffa500",
      "syntax_function": "#ffffff",
      "syntax_section": "#00ffff",
      "column_file": "#1a1a1a",
      "column_rule": "#1e1e1e",
      "column_pattern": "#222222",
      "column_offset": "#262626",
      "column_data": "#2a2a2a",
      "column_hex": "#2e2e2e"
    },
    "font_family": "Consolas",
    "font_size": 10,
    "editor_font_family": "Consolas",
    "editor_font_size": 11,
    "border_radius": 2,
    "border_width": 2,
    "padding_small": 6,
    "padding_medium": 10,
    "padding_large": 14,
    "animation_duration": 100
  },

  "Professional Blue": {
    "name": "Professional Blue",
    "colors": {
      "background": "#1e2328",
      "surface": "#282c34",
      "primary": "#61afef",
      "secondary": "#98c379",
      "accent": "#e06c75",
      
      "text_primary": "#8b92a0",
      "text_secondary": "#5c6370",
      "text_disabled": "#3e4452",
      "text_inverse": "#1e2328",
      
      "button_normal": "#282c34",
      "button_hover": "#3e4452",
      "button_pressed": "#61afef",
      
      "selection_background": "#3e4452",
      "selection_text": "#abb2bf",
      "selection_inactive": "#2c313c",
      "hover_background": "#2c313c",
      
      "editor_background": "#1e2328",
      "editor_text": "#abb2bf",
      "editor_line_number_bg": "#282c34",
      "editor_line_number_text": "#5c6370",
      "editor_current_line": "#2c313c",
      "editor_selection": "#3e4452",
      
      "table_background": "#1e2328",
      "table_alternate": "#252a30",
      "table_header_bg": "#3e4452",
      "table_header_text": "#abb2bf",
      "table_border": "#5c6370",
      
      "success": "#98c379",
      "warning": "#e5c07b",
      "error": "#e06c75",
      "info": "#56b6c2",
      
      "splitter_handle": "#5c6370",
      "splitter_pressed": "#61afef",
      
      "tab_active_bg": "#1e2328",
      "tab_active_text": "#abb2bf",
      "tab_inactive_bg": "#282c34",
      "tab_inactive_text": "#5c6370",
      
      "scrollbar_background": "#1e2328",
      "scrollbar_handle": "#5c6370",
      "scrollbar_handle_hover": "#61afef",
      "checkbox_background": "#1e2328",
      "checkbox_border": "#5c6370",
      "checkbox_checked_border": "#61afef",
      "checkbox_checked_mark": "#61afef",
      "checkbox_hover_border": "#98c379",
      "checkbox_indeterminate": "#e5c07b",
      "syntax_keyword": "#c678dd",
      "syntax_logic": "#61afef",
      "syntax_builtin": "#56b6c2",
      "syntax_modifier": "#e5c07b",
      "syntax_module": "#98c379",
      "syntax_symbol": "#e06c75",
      "syntax_number": "#d19a66",
      "syntax_string": "#98c379",
      "syntax_regex": "#be5046",
      "syntax_hex": "#d19a66",
      "syntax_comment": "#5c6370",
      "syntax_identifier": "#e06c75",
      "syntax_meta_key": "#56b6c2",
      "syntax_tag": "#e5c07b",
      "syntax_condition": "#61afef",
      "syntax_operator": "#abb2bf",
      "syntax_literal": "#98c379",
      "syntax_function": "#98c379",
      "syntax_section": "#c678dd",
      "column_file": "#242730",
      "column_rule": "#252930",
      "column_pattern": "#302925",
      "column_offset": "#2a3025",
      "column_data": "#253025",
      "column_hex": "#252a30"
    },
    "font_family": "Consolas",
    "font_size": 6,
    "editor_font_family": "JetBrains Mono",
    "editor_font_size": 10,
    "border_radius": 4,
    "border_width": 1,
    "padding_small": 4,
    "padding_medium": 8,
    "padding_large": 12,
    "animation_duration": 200
  },

  "Matrix Hacker": {
    "name": "Matrix Hacker",
    "colors": {
      "background": "#000000",
      "surface": "#0d1117",
      "primary": "#00ff41",
      "secondary": "#008f11",
      "accent": "#ff0040",
      
      "text_primary": "#00cc33",
      "text_secondary": "#00aa28",
      "text_disabled": "#004d0d",
      "text_inverse": "#000000",
      
      "button_normal": "#0d1117",
      "button_hover": "#1a1a1a",
      "button_pressed": "#00cc33",
      
      "selection_background": "#ff0040",
      "selection_text": "#ffffff",
      "selection_inactive": "#cc0033",
      "hover_background": "#1a2e1a",
      
      "editor_background": "#000000",
      "editor_text": "#00ff41",
      "editor_line_number_bg": "#0a0a0a",
      "editor_line_number_text": "#008f11",
      "editor_current_line": "#001a00",
      "editor_selection": "#003300",
      
      "table_background": "#000000",
      "table_alternate": "#0a0a0a",
      "table_header_bg": "#1a1a1a",
      "table_header_text": "#00ff41",
      "table_border": "#004d0d",
      
      "success": "#00ff00",
      "warning": "#ffff00",
      "error": "#ff0040",
      "info": "#00ffff",
      
      "splitter_handle": "#004d0d",
      "splitter_pressed": "#00ff41",
      
      "tab_active_bg": "#000000",
      "tab_active_text": "#00ff41",
      "tab_inactive_bg": "#0d1117",
      "tab_inactive_text": "#008f11",
      
      "scrollbar_background": "#000000",
      "scrollbar_handle": "#004d0d",
      "scrollbar_handle_hover": "#00ff41",
      
      "checkbox_background": "#000000",
      "checkbox_border": "#004d0d",
      "checkbox_checked_border": "#00ff41",
      "checkbox_checked_mark": "#00ff41",
      "checkbox_hover_border": "#00cc33",
      "checkbox_indeterminate": "#ffff00",
      
      "syntax_keyword": "#00ffff",
      "syntax_logic": "#ff00ff",
      "syntax_builtin": "#00ff00",
      "syntax_modifier": "#ffff00",
      "syntax_module": "#00ff80",
      "syntax_symbol": "#80ff00",
      "syntax_number": "#ff8000",
      "syntax_string": "#ff4040",
      "syntax_regex": "#ff0080",
      "syntax_hex": "#ffc000",
      "syntax_comment": "#808080",
      "syntax_identifier": "#40ff40",
      "syntax_meta_key": "#00c0ff",
      "syntax_tag": "#c0ff00",
      "syntax_condition": "#ff40ff",
      "syntax_operator": "#ffffff",
      "syntax_literal": "#ff6060",
      "syntax_function": "#60ff60",
      "syntax_section": "#6060ff",
      
      "column_file": "#0a0b0a",
      "column_rule": "#0b0a0b",
      "column_pattern": "#0b0a0a",
      "column_offset": "#0a0b0a",
      "column_data": "#0a0a0b",
      "column_hex": "#0b0b0a"
    },
    "font_family": "Courier New",
    "font_size": 10,
    "editor_font_family": "Courier New",
    "editor_font_size": 8 ,
    "border_radius": 0,
    "border_width": 1,
    "padding_small": 1,
    "padding_medium": 2,
    "padding_large": 3,
    "animation_duration": 100
  },

  "Neon Cyberpunk": {
    "name": "Neon Cyberpunk",
    "colors": {
      "background": "#0a0a0a",
      "surface": "#1a0f1f",
      "primary": "#ff00ff",
      "secondary": "#00ffff",
      "accent": "#ffff00",
      
      "text_primary": "#cc44cc",
      "text_secondary": "#44cccc",
      "text_disabled": "#4d004d",
      "text_inverse": "#0a0a0a",
      
      "button_normal": "#1a0f1f",
      "button_hover": "#330066",
      "button_pressed": "#ff00ff",
      
      "selection_background": "#ffff00",
      "selection_text": "#000000",
      "selection_inactive": "#cccc00",
      "hover_background": "#2a1a3a",
      
      "editor_background": "#0f0f23",
      "editor_text": "#ff00ff",
      "editor_line_number_bg": "#1a0f1f",
      "editor_line_number_text": "#00ffff",
      "editor_current_line": "#1f0f2f",
      "editor_selection": "#3300ff",
      
      "table_background": "#0a0a0a",
      "table_alternate": "#1a0f1f",
      "table_header_bg": "#330066",
      "table_header_text": "#ffff00",
      "table_border": "#ff00ff",
      
      "success": "#00ff7f",
      "warning": "#ff8c00",
      "error": "#ff0080",
      "info": "#00bfff",
      
      "splitter_handle": "#ff00ff",
      "splitter_pressed": "#ffff00",
      
      "tab_active_bg": "#0f0f23",
      "tab_active_text": "#ff00ff",
      "tab_inactive_bg": "#1a0f1f",
      "tab_inactive_text": "#00ffff",
      
      "scrollbar_background": "#0a0a0a",
      "scrollbar_handle": "#ff00ff",
      "scrollbar_handle_hover": "#ffff00",
      
      "checkbox_background": "#0f0f23",
      "checkbox_border": "#ff00ff",
      "checkbox_checked_border": "#ffff00",
      "checkbox_checked_mark": "#ffff00",
      "checkbox_hover_border": "#00ffff",
      "checkbox_indeterminate": "#ff8c00",
      
      "syntax_keyword": "#ff1493",
      "syntax_logic": "#00ff7f",
      "syntax_builtin": "#00bfff",
      "syntax_modifier": "#ffa500",
      "syntax_module": "#da70d6",
      "syntax_symbol": "#ff69b4",
      "syntax_number": "#7fffd4",
      "syntax_string": "#ff6347",
      "syntax_regex": "#ff00ff",
      "syntax_hex": "#ffd700",
      "syntax_comment": "#9370db",
      "syntax_identifier": "#ff4500",
      "syntax_meta_key": "#20b2aa",
      "syntax_tag": "#ffff00",
      "syntax_condition": "#00ff7f",
      "syntax_operator": "#ffffff",
      "syntax_literal": "#ff6347",
      "syntax_function": "#7fff00",
      "syntax_section": "#ff1493",
      
      "column_file": "#12101a",
      "column_rule": "#1a1012",
      "column_pattern": "#101a12",
      "column_offset": "#1a1210",
      "column_data": "#101a1a",
      "column_hex": "#121a10"
    },
    "font_family": "Arial",
    "font_size": 10,
    "editor_font_family": "Consolas",
    "editor_font_size": 11,
    "border_radius": 8,
    "border_width": 2,
    "padding_small": 6,
    "padding_medium": 10,
    "padding_large": 14,
    "animation_duration": 250
  },

  "Sunset Orange": {
    "name": "Sunset Orange",
    "colors": {
      "background": "#1a1209",
      "surface": "#2d1f0a",
      "primary": "#ff6b35",
      "secondary": "#ff8c42",
      "accent": "#ffaa44",
      
      "text_primary": "#cc7035",
      "text_secondary": "#aa5528",
      "text_disabled": "#664422",
      "text_inverse": "#1a1209",
      
      "button_normal": "#2d1f0a",
      "button_hover": "#4d3315",
      "button_pressed": "#ff6b35",
      
      "selection_background": "#ff6b35",
      "selection_text": "#ffffff",
      "selection_inactive": "#cc5529",
      "hover_background": "#3d2b15",
      
      "editor_background": "#0f0b06",
      "editor_text": "#ff8c42",
      "editor_line_number_bg": "#1a1209",
      "editor_line_number_text": "#cc6633",
      "editor_current_line": "#2a1d0f",
      "editor_selection": "#4d3315",
      
      "table_background": "#1a1209",
      "table_alternate": "#2d1f0a",
      "table_header_bg": "#4d3315",
      "table_header_text": "#ffaa44",
      "table_border": "#663d1a",
      
      "success": "#66cc33",
      "warning": "#ffcc00",
      "error": "#ff4444",
      "info": "#4499ff",
      
      "splitter_handle": "#663d1a",
      "splitter_pressed": "#ff6b35",
      
      "tab_active_bg": "#1a1209",
      "tab_active_text": "#ff8c42",
      "tab_inactive_bg": "#2d1f0a",
      "tab_inactive_text": "#cc6633",
      
      "scrollbar_background": "#0f0b06",
      "scrollbar_handle": "#663d1a",
      "scrollbar_handle_hover": "#ff6b35",
      
      "checkbox_background": "#1a1209",
      "checkbox_border": "#663d1a",
      "checkbox_checked_border": "#ff6b35",
      "checkbox_checked_mark": "#ff6b35",
      "checkbox_hover_border": "#ff8c42",
      "checkbox_indeterminate": "#ffaa44",
      
      "syntax_keyword": "#ff9955",
      "syntax_logic": "#ffbb66",
      "syntax_builtin": "#ff7733",
      "syntax_modifier": "#ffcc77",
      "syntax_module": "#ff6622",
      "syntax_symbol": "#ff8844",
      "syntax_number": "#ffdd88",
      "syntax_string": "#ff5511",
      "syntax_regex": "#ff4400",
      "syntax_hex": "#ffcc00",
      "syntax_comment": "#996644",
      "syntax_identifier": "#ffaa55",
      "syntax_meta_key": "#ff7722",
      "syntax_tag": "#ffbb44",
      "syntax_condition": "#ff8833",
      "syntax_operator": "#ffffff",
      "syntax_literal": "#ff6611",
      "syntax_function": "#ff9944",
      "syntax_section": "#ffaa33",
      
      "column_file": "#1e1611",
      "column_rule": "#1a1813",
      "column_pattern": "#1c1615",
      "column_offset": "#181a13",
      "column_data": "#161c15",
      "column_hex": "#141e17"
    },
    "font_family": "Cascadia Code",
    "font_size": 9,
    "editor_font_family": "Cascadia Code",
    "editor_font_size": 8,
    "border_radius": 1,
    "border_width": 1,
    "padding_small": 1,
    "padding_medium": 2,
    "padding_large": 3,
    "animation_duration": 50
  },

  "Ocean Breeze": {
    "name": "Ocean Breeze",
    "colors": {
      "background": "#0a1421",
      "surface": "#152a3e",
      "primary": "#26c6da",
      "secondary": "#4dd0e1",
      "accent": "#80deea",
      
      "text_primary": "#88b3cc",
      "text_secondary": "#6699bb",
      "text_disabled": "#455a64",
      "text_inverse": "#0a1421",
      
      "button_normal": "#152a3e",
      "button_hover": "#1e3a52",
      "button_pressed": "#26c6da",
      
      "selection_background": "#26c6da",
      "selection_text": "#000000",
      "selection_inactive": "#1976d2",
      "hover_background": "#1e3a52",
      
      "editor_background": "#0d1b2a",
      "editor_text": "#b3e5fc",
      "editor_line_number_bg": "#152a3e",
      "editor_line_number_text": "#546e7a",
      "editor_current_line": "#1a2332",
      "editor_selection": "#264653",
      
      "table_background": "#0a1421",
      "table_alternate": "#152a3e",
      "table_header_bg": "#1e3a52",
      "table_header_text": "#b3e5fc",
      "table_border": "#37474f",
      
      "success": "#4caf50",
      "warning": "#ff9800",
      "error": "#f44336",
      "info": "#2196f3",
      
      "splitter_handle": "#37474f",
      "splitter_pressed": "#26c6da",
      
      "tab_active_bg": "#0a1421",
      "tab_active_text": "#b3e5fc",
      "tab_inactive_bg": "#152a3e",
      "tab_inactive_text": "#81d4fa",
      
      "scrollbar_background": "#0d1b2a",
      "scrollbar_handle": "#37474f",
      "scrollbar_handle_hover": "#26c6da",
      
      "checkbox_background": "#0a1421",
      "checkbox_border": "#37474f",
      "checkbox_checked_border": "#26c6da",
      "checkbox_checked_mark": "#26c6da",
      "checkbox_hover_border": "#4dd0e1",
      "checkbox_indeterminate": "#ff9800",
      
      "syntax_keyword": "#64b5f6",
      "syntax_logic": "#81c784",
      "syntax_builtin": "#ffb74d",
      "syntax_modifier": "#f06292",
      "syntax_module": "#ba68c8",
      "syntax_symbol": "#4fc3f7",
      "syntax_number": "#aed581",
      "syntax_string": "#ffcc02",
      "syntax_regex": "#ff8a65",
      "syntax_hex": "#dce775",
      "syntax_comment": "#78909c",
      "syntax_identifier": "#26c6da",
      "syntax_meta_key": "#ffb74d",
      "syntax_tag": "#f06292",
      "syntax_condition": "#81c784",
      "syntax_operator": "#e1f5fe",
      "syntax_literal": "#ffcc02",
      "syntax_function": "#ba68c8",
      "syntax_section": "#64b5f6",
      
      "column_file": "#101821",
      "column_rule": "#111920",
      "column_pattern": "#121a1f",
      "column_offset": "#20181a",
      "column_data": "#18201a",
      "column_hex": "#1a1820"
    },
    "font_family": "Segoe UI",
    "font_size": 9,
    "editor_font_family": "Consolas",
    "editor_font_size": 10,
    "border_radius": 6,
    "border_width": 1,
    "padding_small": 4,
    "padding_medium": 8,
    "padding_large": 12,
    "animation_duration": 180
  },

  "Forest Twilight": {
    "name": "Forest Twilight",
    "colors": {
      "background": "#1a2f1a",
      "surface": "#2d4a2d",
      "primary": "#66bb6a",
      "secondary": "#81c784",
      "accent": "#a5d6a7",
      
      "text_primary": "#99bb9a",
      "text_secondary": "#88aa89",
      "text_disabled": "#4e6e4e",
      "text_inverse": "#1a2f1a",
      
      "button_normal": "#2d4a2d",
      "button_hover": "#3e5e3e",
      "button_pressed": "#66bb6a",
      
      "selection_background": "#66bb6a",
      "selection_text": "#000000",
      "selection_inactive": "#388e3c",
      "hover_background": "#3e5e3e",
      
      "editor_background": "#162e16",
      "editor_text": "#c8e6c9",
      "editor_line_number_bg": "#2d4a2d",
      "editor_line_number_text": "#689f38",
      "editor_current_line": "#223322",
      "editor_selection": "#2e7d32",
      
      "table_background": "#1a2f1a",
      "table_alternate": "#2d4a2d",
      "table_header_bg": "#3e5e3e",
      "table_header_text": "#c8e6c9",
      "table_border": "#558b2f",
      
      "success": "#4caf50",
      "warning": "#ffb300",
      "error": "#d32f2f",
      "info": "#1976d2",
      
      "splitter_handle": "#558b2f",
      "splitter_pressed": "#66bb6a",
      
      "tab_active_bg": "#1a2f1a",
      "tab_active_text": "#c8e6c9",
      "tab_inactive_bg": "#2d4a2d",
      "tab_inactive_text": "#a5d6a7",
      
      "scrollbar_background": "#162e16",
      "scrollbar_handle": "#558b2f",
      "scrollbar_handle_hover": "#66bb6a",
      
      "checkbox_background": "#1a2f1a",
      "checkbox_border": "#558b2f",
      "checkbox_checked_border": "#66bb6a",
      "checkbox_checked_mark": "#66bb6a",
      "checkbox_hover_border": "#81c784",
      "checkbox_indeterminate": "#ffb300",
      
      "syntax_keyword": "#8bc34a",
      "syntax_logic": "#cddc39",
      "syntax_builtin": "#ffcc02",
      "syntax_modifier": "#ff9800",
      "syntax_module": "#795548",
      "syntax_symbol": "#4caf50",
      "syntax_number": "#c5e1a5",
      "syntax_string": "#dcedc8",
      "syntax_regex": "#aed581",
      "syntax_hex": "#f1f8e9",
      "syntax_comment": "#689f38",
      "syntax_identifier": "#66bb6a",
      "syntax_meta_key": "#ffcc02",
      "syntax_tag": "#ff9800",
      "syntax_condition": "#cddc39",
      "syntax_operator": "#f1f8e9",
      "syntax_literal": "#dcedc8",
      "syntax_function": "#795548",
      "syntax_section": "#8bc34a",
      
      "column_file": "#1e2a1e",
      "column_rule": "#1f2b1f",
      "column_pattern": "#2a1e22",
      "column_offset": "#242a1e",
      "column_data": "#1e242a",
      "column_hex": "#222a1e"
    },
    "font_family": "Segoe UI",
    "font_size": 9,
    "editor_font_family": "Consolas",
    "editor_font_size": 10,
    "border_radius": 5,
    "border_width": 1,
    "padding_small": 4,
    "padding_medium": 8,
    "padding_large": 12,
    "animation_duration": 200
  },

  "Lavender Dreams": {
    "name": "Lavender Dreams",
    "colors": {
      "background": "#2a1e3d",
      "surface": "#3d2c5a",
      "primary": "#ba68c8",
      "secondary": "#ce93d8",
      "accent": "#e1bee7",
      
      "text_primary": "#b5a3bb",
      "text_secondary": "#a599aa",
      "text_disabled": "#5e4e6e",
      "text_inverse": "#2a1e3d",
      
      "button_normal": "#3d2c5a",
      "button_hover": "#4e3f6e",
      "button_pressed": "#ba68c8",
      
      "selection_background": "#ba68c8",
      "selection_text": "#ffffff",
      "selection_inactive": "#7b1fa2",
      "hover_background": "#4e3f6e",
      
      "editor_background": "#241b35",
      "editor_text": "#f3e5f5",
      "editor_line_number_bg": "#3d2c5a",
      "editor_line_number_text": "#9c27b0",
      "editor_current_line": "#332545",
      "editor_selection": "#6a1b9a",
      
      "table_background": "#2a1e3d",
      "table_alternate": "#3d2c5a",
      "table_header_bg": "#4e3f6e",
      "table_header_text": "#f3e5f5",
      "table_border": "#673ab7",
      
      "success": "#4caf50",
      "warning": "#ff9800",
      "error": "#f44336",
      "info": "#2196f3",
      
      "splitter_handle": "#673ab7",
      "splitter_pressed": "#ba68c8",
      
      "tab_active_bg": "#2a1e3d",
      "tab_active_text": "#f3e5f5",
      "tab_inactive_bg": "#3d2c5a",
      "tab_inactive_text": "#e1bee7",
      
      "scrollbar_background": "#241b35",
      "scrollbar_handle": "#673ab7",
      "scrollbar_handle_hover": "#ba68c8",
      
      "checkbox_background": "#2a1e3d",
      "checkbox_border": "#673ab7",
      "checkbox_checked_border": "#ba68c8",
      "checkbox_checked_mark": "#ba68c8",
      "checkbox_hover_border": "#ce93d8",
      "checkbox_indeterminate": "#ff9800",
      
      "syntax_keyword": "#ab47bc",
      "syntax_logic": "#e91e63",
      "syntax_builtin": "#ff9800",
      "syntax_modifier": "#ffb74d",
      "syntax_module": "#795548",
      "syntax_symbol": "#9c27b0",
      "syntax_number": "#d1c4e9",
      "syntax_string": "#f8bbd9",
      "syntax_regex": "#ff80ab",
      "syntax_hex": "#ffcdd2",
      "syntax_comment": "#9575cd",
      "syntax_identifier": "#ba68c8",
      "syntax_meta_key": "#ff9800",
      "syntax_tag": "#ffb74d",
      "syntax_condition": "#e91e63",
      "syntax_operator": "#f8bbd9",
      "syntax_literal": "#f8bbd9",
      "syntax_function": "#795548",
      "syntax_section": "#ab47bc",
      
      "column_file": "#2e253d",
      "column_rule": "#2d263c",
      "column_pattern": "#3d252e",
      "column_offset": "#3c2d25",
      "column_data": "#253d2d",
      "column_hex": "#2e3d25"
    },
    "font_family": "Segoe UI",
    "font_size": 9,
    "editor_font_family": "Consolas",
    "editor_font_size": 10,
    "border_radius": 8,
    "border_width": 1,
    "padding_small": 5,
    "padding_medium": 10,
    "padding_large": 15,
    "animation_duration": 220
  }
}